Metadata-Version: 1.0
Name: abita-distributions
Version: 1.0
Summary: Gaussian and Binomial distributions
Home-page: UNKNOWN
Author: Abita Ann Augustine
Author-email: abitaaugustine@gmail.com
License: UNKNOWN
Platform: UNKNOWN
